vsutillib/scripts/__init__.py
vsutillib/scripts/apply2files.py
vsutillib/scripts/dsf2wv.py
vsutillib/scripts/mkvrun.py
vsutillib_scripts-1.6.2.dist-info/AUTHORS
vsutillib_scripts-1.6.2.dist-info/LICENSE.txt
vsutillib_scripts-1.6.2.dist-info/METADATA
vsutillib_scripts-1.6.2.dist-info/WHEEL
vsutillib_scripts-1.6.2.dist-info/top_level.txt
vsutillib_scripts-1.6.2.dist-info/RECORD
