Metadata-Version: 2.1
Name: vsutillib-scripts
Version: 1.6.2
Summary: vsutillib.scripts sub package part of vsutillib
Home-page: https://pypi.org/project/vsutillib-scripts/
Author: Efrain Vergara
Author-email: akai10tsuki@gmail.com
License: MIT
Platform: UNKNOWN
Requires-Python: >=3.8.1, <3.9
Requires-Dist: vsutillib-files (>=1.6.3)
Requires-Dist: vsutillib-media (>=1.6.2)
Requires-Dist: vsutillib-mkv (>=1.6.2)
Requires-Dist: vsutillib-process (>=1.6.0)
